medio/__init__.py
medio/read_save.py
medio/backends/__init__.py
medio/backends/itk_io.py
medio/backends/nib_io.py
medio/backends/pdcm_io.py
medio/backends/pdcm_unpack_ds.py
medio/medimg/__init__.py
medio/medimg/medimg.py
medio/metadata/__init__.py
medio/metadata/affine.py
medio/metadata/convert_nib_itk.py
medio/metadata/dcm_uid.py
medio/metadata/itk_orientation.py
medio/metadata/metadata.py
medio/metadata/pdcm_ds.py
medio/utils/__init__.py
medio/utils/explicit_slicing.py
medio/utils/files.py
medio/utils/two_way_dict.py
medio-0.4.3.dist-info/METADATA
medio-0.4.3.dist-info/WHEEL
medio-0.4.3.dist-info/licenses/LICENSE
medio-0.4.3.dist-info/RECORD
