Metadata-Version: 2.4
Name: medio
Version: 0.4.3
Summary: Medical images I/O Python package
Project-URL: Repository, https://github.com/RSIP-Vision/medio
Project-URL: Bug Tracker, https://github.com/RSIP-Vision/medio/issues
Author-email: RSIP Vision <info@rsipvision.com>, Jonathan Daniel <jonathand655@gmail.com>
License-Expression: Apache-2.0
License-File: LICENSE
Keywords: IO,itk,medical-images,nibabel,pydicom
Classifier: Development Status :: 4 - Beta
Classifier: Intended Audience :: Developers
Classifier: Intended Audience :: Education
Classifier: Intended Audience :: Healthcare Industry
Classifier: Intended Audience :: Science/Research
Classifier: License :: OSI Approved :: Apache Software License
Classifier: Operating System :: OS Independent
Classifier: Programming Language :: Python :: 3 :: Only
Classifier: Programming Language :: Python :: 3.7
Classifier: Programming Language :: Python :: 3.8
Classifier: Programming Language :: Python :: 3.9
Classifier: Topic :: Scientific/Engineering :: Artificial Intelligence
Classifier: Topic :: Scientific/Engineering :: Bio-Informatics
Classifier: Topic :: Scientific/Engineering :: Image Processing
Classifier: Topic :: Scientific/Engineering :: Medical Science Apps.
Classifier: Topic :: Software Development :: Libraries :: Python Modules
Requires-Python: ~=3.7
Requires-Dist: dicom-numpy
Requires-Dist: itk
Requires-Dist: nibabel
Requires-Dist: pydicom
Provides-Extra: test
Requires-Dist: pytest<8.4.2; (python_version < '3.9') and extra == 'test'
Requires-Dist: pytest<9,>=8.4.2; (python_version >= '3.9') and extra == 'test'
